{
  "businessName": "Your Business Name",
  "businessLegalName": "Your Business Legal Name Co., Ltd.",
  "businessType": "Organization",
  "businessDescription": "Your business description for structured data and AI engines.",
  "businessFoundingDate": "2024-01-01",
  "businessUrl": "https://yourdomain.com",
  "businessLogo": "/logo.svg",
  "businessImage": "/images/og-default.jpg",
  "businessPhone": "",
  "businessEmail": "",
  "businessPriceRange": "",
  "addressStreetAddress": "",
  "addressCity": "",
  "addressRegion": "",
  "addressPostalCode": "",
  "addressCountry": "",
  "geoLatitude": null,
  "geoLongitude": null,
  "openingHours": [],
  "socialTwitter": "",
  "socialFacebook": "",
  "socialInstagram": "",
  "socialLinkedin": "",
  "socialYoutube": "",
  "socialGithub": "",
  "socialNaver": "",
  "googleAnalyticsId": "",
  "googleTagManagerId": "",
  "googleSearchConsoleVerification": "",
  "naverSearchAdvisorVerification": "",
  "naverAnalyticsId": "",
  "microsoftClarityId": "",
  "facebookPixelId": "",
  "kakaoPixelId": "",
  "customHeadCode": "",
  "enableLocalBusiness": false,
  "enableFaqSchema": true,
  "enableBreadcrumbSchema": true,
  "allowGPTBot": true,
  "allowClaudeBot": true,
  "allowPerplexityBot": true,
  "allowGoogleExtended": true
}
